{
  "annotations": {
    "list": [
      {
        "builtIn": 1,
        "datasource": {
          "type": "grafana",
          "uid": "-- Grafana --"
        },
        "enable": true,
        "hide": true,
        "iconColor": "rgba(0, 211, 255, 1)",
        "name": "Annotations & Alerts",
        "target": {
          "limit": 100,
          "matchAny": false,
          "tags": [],
          "type": "dashboard"
        },
        "type": "dashboard"
      }
    ]
  },
  "editable": true,
  "fiscalYearStartMonth": 0,
  "graphTooltip": 0,
  "id": 1,
  "links": [],
  "liveNow": false,
  "panels": [
    {
      "collapsed": false,
      "gridPos": {
        "h": 1,
        "w": 24,
        "x": 0,
        "y": 0
      },
      "id": 28,
      "panels": [],
      "title": "Fishing",
      "type": "row"
    },
    {
      "datasource": {
        "type": "prometheus",
        "uid": "I50WY3hVz"
      },
      "description": "",
      "fieldConfig": {
        "defaults": {
          "color": {
            "mode": "palette-classic"
          },
          "custom": {
            "axisLabel": "",
            "axisPlacement": "auto",
            "barAlignment": 0,
            "drawStyle": "line",
            "fillOpacity": 0,
            "gradientMode": "none",
            "hideFrom": {
              "legend": false,
              "tooltip": false,
              "viz": false
            },
            "lineInterpolation": "linear",
            "lineWidth": 1,
            "pointSize": 5,
            "scaleDistribution": {
              "type": "linear"
            },
            "showPoints": "auto",
            "spanNulls": false,
            "stacking": {
              "group": "A",
              "mode": "none"
            },
            "thresholdsStyle": {
              "mode": "off"
            }
          },
          "mappings": [],
          "thresholds": {
            "mode": "absolute",
            "steps": [
              {
                "color": "green",
                "value": null
              },
              {
                "color": "red",
                "value": 80
              }
            ]
          }
        },
        "overrides": []
      },
      "gridPos": {
        "h": 8,
        "w": 4,
        "x": 0,
        "y": 1
      },
      "id": 24,
      "options": {
        "legend": {
          "calcs": [],
          "displayMode": "list",
          "placement": "bottom"
        },
        "tooltip": {
          "mode": "single",
          "sort": "none"
        }
      },
      "targets": [
        {
          "datasource": {
            "type": "prometheus",
            "uid": "I50WY3hVz"
          },
          "editorMode": "code",
          "exemplar": false,
          "expr": "auction_price_gold{name=\"Scalebelly Mackerel\", quantile=\"$percentile\"}",
          "format": "time_series",
          "hide": false,
          "instant": false,
          "legendFormat": "{{quantile}}",
          "range": true,
          "refId": "A"
        }
      ],
      "title": "Scalebelly Mackerel",
      "type": "timeseries"
    },
    {
      "datasource": {
        "type": "prometheus",
        "uid": "I50WY3hVz"
      },
      "description": "",
      "fieldConfig": {
        "defaults": {
          "color": {
            "mode": "palette-classic"
          },
          "custom": {
            "axisLabel": "",
            "axisPlacement": "auto",
            "barAlignment": 0,
            "drawStyle": "line",
            "fillOpacity": 0,
            "gradientMode": "none",
            "hideFrom": {
              "legend": false,
              "tooltip": false,
              "viz": false
            },
            "lineInterpolation": "linear",
            "lineWidth": 1,
            "pointSize": 5,
            "scaleDistribution": {
              "type": "linear"
            },
            "showPoints": "auto",
            "spanNulls": false,
            "stacking": {
              "group": "A",
              "mode": "none"
            },
            "thresholdsStyle": {
              "mode": "off"
            }
          },
          "mappings": [],
          "thresholds": {
            "mode": "absolute",
            "steps": [
              {
                "color": "green",
                "value": null
              },
              {
                "color": "red",
                "value": 80
              }
            ]
          }
        },
        "overrides": []
      },
      "gridPos": {
        "h": 8,
        "w": 4,
        "x": 4,
        "y": 1
      },
      "id": 40,
      "options": {
        "legend": {
          "calcs": [],
          "displayMode": "list",
          "placement": "bottom"
        },
        "tooltip": {
          "mode": "single",
          "sort": "none"
        }
      },
      "targets": [
        {
          "datasource": {
            "type": "prometheus",
            "uid": "I50WY3hVz"
          },
          "editorMode": "code",
          "exemplar": false,
          "expr": "auction_price_gold{name=\"Thousandbite Piranha\", quantile=\"$percentile\"}",
          "format": "time_series",
          "hide": false,
          "instant": false,
          "legendFormat": "{{quantile}}",
          "range": true,
          "refId": "A"
        }
      ],
      "title": "Thousandbite Piranha",
      "type": "timeseries"
    },
    {
      "datasource": {
        "type": "prometheus",
        "uid": "I50WY3hVz"
      },
      "description": "",
      "fieldConfig": {
        "defaults": {
          "color": {
            "mode": "palette-classic"
          },
          "custom": {
            "axisLabel": "",
            "axisPlacement": "auto",
            "barAlignment": 0,
            "drawStyle": "line",
            "fillOpacity": 0,
            "gradientMode": "none",
            "hideFrom": {
              "legend": false,
              "tooltip": false,
              "viz": false
            },
            "lineInterpolation": "linear",
            "lineWidth": 1,
            "pointSize": 5,
            "scaleDistribution": {
              "type": "linear"
            },
            "showPoints": "auto",
            "spanNulls": false,
            "stacking": {
              "group": "A",
              "mode": "none"
            },
            "thresholdsStyle": {
              "mode": "off"
            }
          },
          "mappings": [],
          "thresholds": {
            "mode": "absolute",
            "steps": [
              {
                "color": "green",
                "value": null
              },
              {
                "color": "red",
                "value": 80
              }
            ]
          }
        },
        "overrides": []
      },
      "gridPos": {
        "h": 8,
        "w": 4,
        "x": 8,
        "y": 1
      },
      "id": 39,
      "options": {
        "legend": {
          "calcs": [],
          "displayMode": "list",
          "placement": "bottom"
        },
        "tooltip": {
          "mode": "single",
          "sort": "none"
        }
      },
      "targets": [
        {
          "datasource": {
            "type": "prometheus",
            "uid": "I50WY3hVz"
          },
          "editorMode": "code",
          "exemplar": false,
          "expr": "auction_price_gold{name=\"Aileron Seamoth\", quantile=\"$percentile\"}",
          "format": "time_series",
          "hide": false,
          "instant": false,
          "legendFormat": "{{quantile}}",
          "range": true,
          "refId": "A"
        }
      ],
      "title": "Aileron Seamoth",
      "type": "timeseries"
    },
    {
      "datasource": {
        "type": "prometheus",
        "uid": "I50WY3hVz"
      },
      "description": "",
      "fieldConfig": {
        "defaults": {
          "color": {
            "mode": "palette-classic"
          },
          "custom": {
            "axisLabel": "",
            "axisPlacement": "auto",
            "barAlignment": 0,
            "drawStyle": "line",
            "fillOpacity": 0,
            "gradientMode": "none",
            "hideFrom": {
              "legend": false,
              "tooltip": false,
              "viz": false
            },
            "lineInterpolation": "linear",
            "lineWidth": 1,
            "pointSize": 5,
            "scaleDistribution": {
              "type": "linear"
            },
            "showPoints": "auto",
            "spanNulls": false,
            "stacking": {
              "group": "A",
              "mode": "none"
            },
            "thresholdsStyle": {
              "mode": "off"
            }
          },
          "mappings": [],
          "thresholds": {
            "mode": "absolute",
            "steps": [
              {
                "color": "green",
                "value": null
              },
              {
                "color": "red",
                "value": 80
              }
            ]
          }
        },
        "overrides": []
      },
      "gridPos": {
        "h": 8,
        "w": 4,
        "x": 12,
        "y": 1
      },
      "id": 38,
      "options": {
        "legend": {
          "calcs": [],
          "displayMode": "list",
          "placement": "bottom"
        },
        "tooltip": {
          "mode": "single",
          "sort": "none"
        }
      },
      "targets": [
        {
          "datasource": {
            "type": "prometheus",
            "uid": "I50WY3hVz"
          },
          "editorMode": "code",
          "exemplar": false,
          "expr": "auction_price_gold{name=\"Cerulean Spinefish\", quantile=\"$percentile\"}",
          "format": "time_series",
          "hide": false,
          "instant": false,
          "legendFormat": "{{quantile}}",
          "range": true,
          "refId": "A"
        }
      ],
      "title": "Cerulean Spinefish",
      "type": "timeseries"
    },
    {
      "datasource": {
        "type": "prometheus",
        "uid": "I50WY3hVz"
      },
      "description": "",
      "fieldConfig": {
        "defaults": {
          "color": {
            "mode": "palette-classic"
          },
          "custom": {
            "axisLabel": "",
            "axisPlacement": "auto",
            "barAlignment": 0,
            "drawStyle": "line",
            "fillOpacity": 0,
            "gradientMode": "none",
            "hideFrom": {
              "legend": false,
              "tooltip": false,
              "viz": false
            },
            "lineInterpolation": "linear",
            "lineWidth": 1,
            "pointSize": 5,
            "scaleDistribution": {
              "type": "linear"
            },
            "showPoints": "auto",
            "spanNulls": false,
            "stacking": {
              "group": "A",
              "mode": "none"
            },
            "thresholdsStyle": {
              "mode": "off"
            }
          },
          "mappings": [],
          "thresholds": {
            "mode": "absolute",
            "steps": [
              {
                "color": "green",
                "value": null
              },
              {
                "color": "red",
                "value": 80
              }
            ]
          }
        },
        "overrides": []
      },
      "gridPos": {
        "h": 8,
        "w": 4,
        "x": 16,
        "y": 1
      },
      "id": 37,
      "options": {
        "legend": {
          "calcs": [],
          "displayMode": "list",
          "placement": "bottom"
        },
        "tooltip": {
          "mode": "single",
          "sort": "none"
        }
      },
      "targets": [
        {
          "datasource": {
            "type": "prometheus",
            "uid": "I50WY3hVz"
          },
          "editorMode": "code",
          "exemplar": false,
          "expr": "auction_price_gold{name=\"Temporal Dragonhead\", quantile=\"$percentile\"}",
          "format": "time_series",
          "hide": false,
          "instant": false,
          "legendFormat": "{{quantile}}",
          "range": true,
          "refId": "A"
        }
      ],
      "title": "Temporal Dragonhead",
      "type": "timeseries"
    },
    {
      "datasource": {
        "type": "prometheus",
        "uid": "I50WY3hVz"
      },
      "description": "",
      "fieldConfig": {
        "defaults": {
          "color": {
            "mode": "palette-classic"
          },
          "custom": {
            "axisLabel": "",
            "axisPlacement": "auto",
            "barAlignment": 0,
            "drawStyle": "line",
            "fillOpacity": 0,
            "gradientMode": "none",
            "hideFrom": {
              "legend": false,
              "tooltip": false,
              "viz": false
            },
            "lineInterpolation": "linear",
            "lineWidth": 1,
            "pointSize": 5,
            "scaleDistribution": {
              "type": "linear"
            },
            "showPoints": "auto",
            "spanNulls": false,
            "stacking": {
              "group": "A",
              "mode": "none"
            },
            "thresholdsStyle": {
              "mode": "off"
            }
          },
          "mappings": [],
          "thresholds": {
            "mode": "absolute",
            "steps": [
              {
                "color": "green",
                "value": null
              },
              {
                "color": "red",
                "value": 80
              }
            ]
          }
        },
        "overrides": []
      },
      "gridPos": {
        "h": 8,
        "w": 4,
        "x": 20,
        "y": 1
      },
      "id": 36,
      "options": {
        "legend": {
          "calcs": [],
          "displayMode": "list",
          "placement": "bottom"
        },
        "tooltip": {
          "mode": "single",
          "sort": "none"
        }
      },
      "targets": [
        {
          "datasource": {
            "type": "prometheus",
            "uid": "I50WY3hVz"
          },
          "editorMode": "code",
          "exemplar": false,
          "expr": "auction_price_gold{name=\"Islefin Dorado\", quantile=\"$percentile\"}",
          "format": "time_series",
          "hide": false,
          "instant": false,
          "legendFormat": "{{quantile}}",
          "range": true,
          "refId": "A"
        }
      ],
      "title": "Islefin Dorado",
      "type": "timeseries"
    },
    {
      "datasource": {
        "type": "prometheus",
        "uid": "I50WY3hVz"
      },
      "description": "",
      "fieldConfig": {
        "defaults": {
          "color": {
            "mode": "palette-classic"
          },
          "custom": {
            "axisLabel": "",
            "axisPlacement": "auto",
            "barAlignment": 0,
            "drawStyle": "line",
            "fillOpacity": 0,
            "gradientMode": "none",
            "hideFrom": {
              "legend": false,
              "tooltip": false,
              "viz": false
            },
            "lineInterpolation": "linear",
            "lineWidth": 1,
            "pointSize": 5,
            "scaleDistribution": {
              "type": "linear"
            },
            "showPoints": "auto",
            "spanNulls": false,
            "stacking": {
              "group": "A",
              "mode": "none"
            },
            "thresholdsStyle": {
              "mode": "off"
            }
          },
          "mappings": [],
          "thresholds": {
            "mode": "absolute",
            "steps": [
              {
                "color": "green",
                "value": null
              },
              {
                "color": "red",
                "value": 80
              }
            ]
          }
        },
        "overrides": []
      },
      "gridPos": {
        "h": 8,
        "w": 4,
        "x": 0,
        "y": 9
      },
      "id": 35,
      "options": {
        "legend": {
          "calcs": [],
          "displayMode": "list",
          "placement": "bottom"
        },
        "tooltip": {
          "mode": "single",
          "sort": "none"
        }
      },
      "targets": [
        {
          "datasource": {
            "type": "prometheus",
            "uid": "I50WY3hVz"
          },
          "editorMode": "code",
          "exemplar": false,
          "expr": "auction_price_gold{name=\"Magma Thresher\", quantile=\"$percentile\"}",
          "format": "time_series",
          "hide": false,
          "instant": false,
          "legendFormat": "{{quantile}}",
          "range": true,
          "refId": "A"
        }
      ],
      "title": "Magma Thresher",
      "type": "timeseries"
    },
    {
      "datasource": {
        "type": "prometheus",
        "uid": "I50WY3hVz"
      },
      "description": "",
      "fieldConfig": {
        "defaults": {
          "color": {
            "mode": "palette-classic"
          },
          "custom": {
            "axisLabel": "",
            "axisPlacement": "auto",
            "barAlignment": 0,
            "drawStyle": "line",
            "fillOpacity": 0,
            "gradientMode": "none",
            "hideFrom": {
              "legend": false,
              "tooltip": false,
              "viz": false
            },
            "lineInterpolation": "linear",
            "lineWidth": 1,
            "pointSize": 5,
            "scaleDistribution": {
              "type": "linear"
            },
            "showPoints": "auto",
            "spanNulls": false,
            "stacking": {
              "group": "A",
              "mode": "none"
            },
            "thresholdsStyle": {
              "mode": "off"
            }
          },
          "mappings": [],
          "thresholds": {
            "mode": "absolute",
            "steps": [
              {
                "color": "green",
                "value": null
              },
              {
                "color": "red",
                "value": 80
              }
            ]
          }
        },
        "overrides": []
      },
      "gridPos": {
        "h": 8,
        "w": 4,
        "x": 4,
        "y": 9
      },
      "id": 34,
      "options": {
        "legend": {
          "calcs": [],
          "displayMode": "list",
          "placement": "bottom"
        },
        "tooltip": {
          "mode": "single",
          "sort": "none"
        }
      },
      "targets": [
        {
          "datasource": {
            "type": "prometheus",
            "uid": "I50WY3hVz"
          },
          "editorMode": "code",
          "exemplar": false,
          "expr": "auction_price_gold{name=\"Prismatic Leaper\", quantile=\"$percentile\"}",
          "format": "time_series",
          "hide": false,
          "instant": false,
          "legendFormat": "{{quantile}}",
          "range": true,
          "refId": "A"
        }
      ],
      "title": "Prismatic Leaper",
      "type": "timeseries"
    },
    {
      "datasource": {
        "type": "prometheus",
        "uid": "I50WY3hVz"
      },
      "description": "",
      "fieldConfig": {
        "defaults": {
          "color": {
            "mode": "palette-classic"
          },
          "custom": {
            "axisLabel": "",
            "axisPlacement": "auto",
            "barAlignment": 0,
            "drawStyle": "line",
            "fillOpacity": 0,
            "gradientMode": "none",
            "hideFrom": {
              "legend": false,
              "tooltip": false,
              "viz": false
            },
            "lineInterpolation": "linear",
            "lineWidth": 1,
            "pointSize": 5,
            "scaleDistribution": {
              "type": "linear"
            },
            "showPoints": "auto",
            "spanNulls": false,
            "stacking": {
              "group": "A",
              "mode": "none"
            },
            "thresholdsStyle": {
              "mode": "off"
            }
          },
          "mappings": [],
          "thresholds": {
            "mode": "absolute",
            "steps": [
              {
                "color": "green",
                "value": null
              },
              {
                "color": "red",
                "value": 80
              }
            ]
          }
        },
        "overrides": []
      },
      "gridPos": {
        "h": 8,
        "w": 4,
        "x": 8,
        "y": 9
      },
      "id": 33,
      "options": {
        "legend": {
          "calcs": [],
          "displayMode": "list",
          "placement": "bottom"
        },
        "tooltip": {
          "mode": "single",
          "sort": "none"
        }
      },
      "targets": [
        {
          "datasource": {
            "type": "prometheus",
            "uid": "I50WY3hVz"
          },
          "editorMode": "code",
          "exemplar": false,
          "expr": "auction_price_gold{name=\"Frosted Rimefin Tuna\", quantile=\"$percentile\"}",
          "format": "time_series",
          "hide": false,
          "instant": false,
          "legendFormat": "{{quantile}}",
          "range": true,
          "refId": "A"
        }
      ],
      "title": "Frosted Rimefin Tuna",
      "type": "timeseries"
    },
    {
      "gridPos": {
        "h": 1,
        "w": 24,
        "x": 0,
        "y": 17
      },
      "id": 22,
      "title": "Herbalism",
      "type": "row"
    },
    {
      "datasource": {
        "type": "prometheus",
        "uid": "I50WY3hVz"
      },
      "description": "",
      "fieldConfig": {
        "defaults": {
          "color": {
            "mode": "palette-classic"
          },
          "custom": {
            "axisLabel": "",
            "axisPlacement": "auto",
            "barAlignment": 0,
            "drawStyle": "line",
            "fillOpacity": 0,
            "gradientMode": "none",
            "hideFrom": {
              "legend": false,
              "tooltip": false,
              "viz": false
            },
            "lineInterpolation": "linear",
            "lineWidth": 1,
            "pointSize": 5,
            "scaleDistribution": {
              "type": "linear"
            },
            "showPoints": "auto",
            "spanNulls": false,
            "stacking": {
              "group": "A",
              "mode": "none"
            },
            "thresholdsStyle": {
              "mode": "off"
            }
          },
          "mappings": [],
          "thresholds": {
            "mode": "absolute",
            "steps": [
              {
                "color": "green",
                "value": null
              },
              {
                "color": "red",
                "value": 80
              }
            ]
          }
        },
        "overrides": []
      },
      "gridPos": {
        "h": 8,
        "w": 4,
        "x": 0,
        "y": 18
      },
      "id": 8,
      "options": {
        "legend": {
          "calcs": [],
          "displayMode": "list",
          "placement": "bottom"
        },
        "tooltip": {
          "mode": "single",
          "sort": "none"
        }
      },
      "targets": [
        {
          "datasource": {
            "type": "prometheus",
            "uid": "I50WY3hVz"
          },
          "editorMode": "code",
          "exemplar": false,
          "expr": "auction_price_gold{name=\"Hochenblume\", quantile=\"$percentile\"}",
          "format": "time_series",
          "hide": false,
          "instant": false,
          "legendFormat": "Rank {{rank}}, {{quantile}}",
          "range": true,
          "refId": "A"
        }
      ],
      "title": "Hochenblume",
      "type": "timeseries"
    },
    {
      "datasource": {
        "type": "prometheus",
        "uid": "I50WY3hVz"
      },
      "description": "",
      "fieldConfig": {
        "defaults": {
          "color": {
            "mode": "palette-classic"
          },
          "custom": {
            "axisLabel": "",
            "axisPlacement": "auto",
            "barAlignment": 0,
            "drawStyle": "line",
            "fillOpacity": 0,
            "gradientMode": "none",
            "hideFrom": {
              "legend": false,
              "tooltip": false,
              "viz": false
            },
            "lineInterpolation": "linear",
            "lineWidth": 1,
            "pointSize": 5,
            "scaleDistribution": {
              "type": "linear"
            },
            "showPoints": "auto",
            "spanNulls": false,
            "stacking": {
              "group": "A",
              "mode": "none"
            },
            "thresholdsStyle": {
              "mode": "off"
            }
          },
          "mappings": [],
          "thresholds": {
            "mode": "absolute",
            "steps": [
              {
                "color": "green",
                "value": null
              },
              {
                "color": "red",
                "value": 80
              }
            ]
          }
        },
        "overrides": []
      },
      "gridPos": {
        "h": 8,
        "w": 4,
        "x": 4,
        "y": 18
      },
      "id": 29,
      "options": {
        "legend": {
          "calcs": [],
          "displayMode": "list",
          "placement": "bottom"
        },
        "tooltip": {
          "mode": "single",
          "sort": "none"
        }
      },
      "targets": [
        {
          "datasource": {
            "type": "prometheus",
            "uid": "I50WY3hVz"
          },
          "editorMode": "code",
          "exemplar": false,
          "expr": "auction_price_gold{name=\"Hochenblume\", quantile=\"$percentile\"}",
          "format": "time_series",
          "hide": false,
          "instant": false,
          "legendFormat": "Rank {{rank}}, {{quantile}}",
          "range": true,
          "refId": "A"
        }
      ],
      "title": "Hochenblume",
      "type": "timeseries"
    },
    {
      "datasource": {
        "type": "prometheus",
        "uid": "I50WY3hVz"
      },
      "description": "",
      "fieldConfig": {
        "defaults": {
          "color": {
            "mode": "palette-classic"
          },
          "custom": {
            "axisLabel": "",
            "axisPlacement": "auto",
            "barAlignment": 0,
            "drawStyle": "line",
            "fillOpacity": 0,
            "gradientMode": "none",
            "hideFrom": {
              "legend": false,
              "tooltip": false,
              "viz": false
            },
            "lineInterpolation": "linear",
            "lineWidth": 1,
            "pointSize": 5,
            "scaleDistribution": {
              "type": "linear"
            },
            "showPoints": "auto",
            "spanNulls": false,
            "stacking": {
              "group": "A",
              "mode": "none"
            },
            "thresholdsStyle": {
              "mode": "off"
            }
          },
          "mappings": [],
          "thresholds": {
            "mode": "absolute",
            "steps": [
              {
                "color": "green",
                "value": null
              },
              {
                "color": "red",
                "value": 80
              }
            ]
          }
        },
        "overrides": []
      },
      "gridPos": {
        "h": 8,
        "w": 4,
        "x": 8,
        "y": 18
      },
      "id": 26,
      "options": {
        "legend": {
          "calcs": [],
          "displayMode": "list",
          "placement": "bottom"
        },
        "tooltip": {
          "mode": "single",
          "sort": "none"
        }
      },
      "targets": [
        {
          "datasource": {
            "type": "prometheus",
            "uid": "I50WY3hVz"
          },
          "editorMode": "code",
          "exemplar": false,
          "expr": "auction_price_gold{name=\"Saxifrage\", quantile=\"$percentile\"}",
          "format": "time_series",
          "hide": false,
          "instant": false,
          "legendFormat": "Rank {{rank}}, {{quantile}}",
          "range": true,
          "refId": "A"
        }
      ],
      "title": "Saxifrage",
      "type": "timeseries"
    },
    {
      "datasource": {
        "type": "prometheus",
        "uid": "I50WY3hVz"
      },
      "description": "",
      "fieldConfig": {
        "defaults": {
          "color": {
            "mode": "palette-classic"
          },
          "custom": {
            "axisLabel": "",
            "axisPlacement": "auto",
            "barAlignment": 0,
            "drawStyle": "line",
            "fillOpacity": 0,
            "gradientMode": "none",
            "hideFrom": {
              "legend": false,
              "tooltip": false,
              "viz": false
            },
            "lineInterpolation": "linear",
            "lineWidth": 1,
            "pointSize": 5,
            "scaleDistribution": {
              "type": "linear"
            },
            "showPoints": "auto",
            "spanNulls": false,
            "stacking": {
              "group": "A",
              "mode": "none"
            },
            "thresholdsStyle": {
              "mode": "off"
            }
          },
          "mappings": [],
          "thresholds": {
            "mode": "absolute",
            "steps": [
              {
                "color": "green",
                "value": null
              },
              {
                "color": "red",
                "value": 80
              }
            ]
          }
        },
        "overrides": []
      },
      "gridPos": {
        "h": 8,
        "w": 4,
        "x": 12,
        "y": 18
      },
      "id": 25,
      "options": {
        "legend": {
          "calcs": [],
          "displayMode": "list",
          "placement": "bottom"
        },
        "tooltip": {
          "mode": "single",
          "sort": "none"
        }
      },
      "targets": [
        {
          "datasource": {
            "type": "prometheus",
            "uid": "I50WY3hVz"
          },
          "editorMode": "code",
          "exemplar": false,
          "expr": "auction_price_gold{name=\"Writhebark\", quantile=\"$percentile\"}",
          "format": "time_series",
          "hide": false,
          "instant": false,
          "legendFormat": "Rank {{rank}}, {{quantile}}",
          "range": true,
          "refId": "A"
        }
      ],
      "title": "Writhebark",
      "type": "timeseries"
    },
    {
      "collapsed": false,
      "gridPos": {
        "h": 1,
        "w": 24,
        "x": 0,
        "y": 26
      },
      "id": 14,
      "panels": [],
      "title": "Mining",
      "type": "row"
    },
    {
      "datasource": {
        "type": "prometheus",
        "uid": "I50WY3hVz"
      },
      "fieldConfig": {
        "defaults": {
          "color": {
            "mode": "palette-classic"
          },
          "custom": {
            "axisLabel": "",
            "axisPlacement": "auto",
            "barAlignment": 0,
            "drawStyle": "line",
            "fillOpacity": 0,
            "gradientMode": "none",
            "hideFrom": {
              "legend": false,
              "tooltip": false,
              "viz": false
            },
            "lineInterpolation": "linear",
            "lineWidth": 1,
            "pointSize": 5,
            "scaleDistribution": {
              "type": "linear"
            },
            "showPoints": "auto",
            "spanNulls": false,
            "stacking": {
              "group": "A",
              "mode": "none"
            },
            "thresholdsStyle": {
              "mode": "off"
            }
          },
          "mappings": [],
          "thresholds": {
            "mode": "absolute",
            "steps": [
              {
                "color": "green",
                "value": null
              },
              {
                "color": "red",
                "value": 80
              }
            ]
          }
        },
        "overrides": []
      },
      "gridPos": {
        "h": 8,
        "w": 4,
        "x": 0,
        "y": 27
      },
      "id": 4,
      "options": {
        "legend": {
          "calcs": [],
          "displayMode": "list",
          "placement": "bottom"
        },
        "tooltip": {
          "mode": "single",
          "sort": "none"
        }
      },
      "targets": [
        {
          "datasource": {
            "type": "prometheus",
            "uid": "I50WY3hVz"
          },
          "editorMode": "code",
          "exemplar": false,
          "expr": "auction_price_gold{name=\"Serevite Ore\", quantile=\"$percentile\"}",
          "format": "time_series",
          "hide": false,
          "instant": false,
          "legendFormat": "Rank {{rank}}, {{quantile}}",
          "range": true,
          "refId": "A"
        }
      ],
      "title": "Serevite Ore",
      "type": "timeseries"
    },
    {
      "datasource": {
        "type": "prometheus",
        "uid": "I50WY3hVz"
      },
      "fieldConfig": {
        "defaults": {
          "color": {
            "mode": "palette-classic"
          },
          "custom": {
            "axisLabel": "",
            "axisPlacement": "auto",
            "barAlignment": 0,
            "drawStyle": "line",
            "fillOpacity": 0,
            "gradientMode": "none",
            "hideFrom": {
              "legend": false,
              "tooltip": false,
              "viz": false
            },
            "lineInterpolation": "linear",
            "lineWidth": 1,
            "pointSize": 5,
            "scaleDistribution": {
              "type": "linear"
            },
            "showPoints": "auto",
            "spanNulls": false,
            "stacking": {
              "group": "A",
              "mode": "none"
            },
            "thresholdsStyle": {
              "mode": "off"
            }
          },
          "mappings": [],
          "thresholds": {
            "mode": "absolute",
            "steps": [
              {
                "color": "green",
                "value": null
              },
              {
                "color": "red",
                "value": 80
              }
            ]
          }
        },
        "overrides": []
      },
      "gridPos": {
        "h": 8,
        "w": 4,
        "x": 4,
        "y": 27
      },
      "id": 23,
      "options": {
        "legend": {
          "calcs": [],
          "displayMode": "list",
          "placement": "bottom"
        },
        "tooltip": {
          "mode": "single",
          "sort": "none"
        }
      },
      "targets": [
        {
          "datasource": {
            "type": "prometheus",
            "uid": "I50WY3hVz"
          },
          "editorMode": "code",
          "exemplar": false,
          "expr": "auction_price_gold{name=\"Serevite Ore\", quantile=\"$percentile\"}",
          "format": "time_series",
          "hide": false,
          "instant": false,
          "legendFormat": "Rank {{rank}}, {{quantile}}",
          "range": true,
          "refId": "A"
        }
      ],
      "title": "Serevite Ore",
      "type": "timeseries"
    },
    {
      "datasource": {
        "type": "prometheus",
        "uid": "I50WY3hVz"
      },
      "description": "",
      "fieldConfig": {
        "defaults": {
          "color": {
            "mode": "palette-classic"
          },
          "custom": {
            "axisLabel": "",
            "axisPlacement": "auto",
            "barAlignment": 0,
            "drawStyle": "line",
            "fillOpacity": 0,
            "gradientMode": "none",
            "hideFrom": {
              "legend": false,
              "tooltip": false,
              "viz": false
            },
            "lineInterpolation": "linear",
            "lineWidth": 1,
            "pointSize": 5,
            "scaleDistribution": {
              "type": "linear"
            },
            "showPoints": "auto",
            "spanNulls": false,
            "stacking": {
              "group": "A",
              "mode": "none"
            },
            "thresholdsStyle": {
              "mode": "off"
            }
          },
          "mappings": [],
          "thresholds": {
            "mode": "absolute",
            "steps": [
              {
                "color": "green",
                "value": null
              },
              {
                "color": "red",
                "value": 80
              }
            ]
          }
        },
        "overrides": []
      },
      "gridPos": {
        "h": 8,
        "w": 4,
        "x": 8,
        "y": 27
      },
      "id": 6,
      "options": {
        "legend": {
          "calcs": [],
          "displayMode": "list",
          "placement": "bottom"
        },
        "tooltip": {
          "mode": "single",
          "sort": "none"
        }
      },
      "targets": [
        {
          "datasource": {
            "type": "prometheus",
            "uid": "I50WY3hVz"
          },
          "editorMode": "code",
          "exemplar": false,
          "expr": "auction_price_gold{name=\"Khaz'gorite Ore\", quantile=\"$percentile\"}",
          "format": "time_series",
          "hide": false,
          "instant": false,
          "legendFormat": "Rank {{rank}}, {{quantile}}",
          "range": true,
          "refId": "A"
        }
      ],
      "title": "Khaz'gorite Ore",
      "type": "timeseries"
    },
    {
      "collapsed": false,
      "gridPos": {
        "h": 1,
        "w": 24,
        "x": 0,
        "y": 35
      },
      "id": 18,
      "panels": [],
      "title": "Essence",
      "type": "row"
    },
    {
      "datasource": {
        "type": "prometheus",
        "uid": "I50WY3hVz"
      },
      "description": "",
      "fieldConfig": {
        "defaults": {
          "color": {
            "mode": "palette-classic"
          },
          "custom": {
            "axisLabel": "",
            "axisPlacement": "auto",
            "barAlignment": 0,
            "drawStyle": "line",
            "fillOpacity": 0,
            "gradientMode": "none",
            "hideFrom": {
              "legend": false,
              "tooltip": false,
              "viz": false
            },
            "lineInterpolation": "linear",
            "lineWidth": 1,
            "pointSize": 5,
            "scaleDistribution": {
              "type": "linear"
            },
            "showPoints": "auto",
            "spanNulls": false,
            "stacking": {
              "group": "A",
              "mode": "none"
            },
            "thresholdsStyle": {
              "mode": "off"
            }
          },
          "mappings": [],
          "thresholds": {
            "mode": "absolute",
            "steps": [
              {
                "color": "green",
                "value": null
              },
              {
                "color": "red",
                "value": 80
              }
            ]
          }
        },
        "overrides": []
      },
      "gridPos": {
        "h": 8,
        "w": 4,
        "x": 0,
        "y": 36
      },
      "id": 10,
      "options": {
        "legend": {
          "calcs": [],
          "displayMode": "list",
          "placement": "bottom"
        },
        "tooltip": {
          "mode": "single",
          "sort": "none"
        }
      },
      "targets": [
        {
          "datasource": {
            "type": "prometheus",
            "uid": "I50WY3hVz"
          },
          "editorMode": "code",
          "exemplar": false,
          "expr": "auction_price_gold{name=\"Rousing Earth\", quantile=\"$percentile\"}",
          "format": "time_series",
          "hide": false,
          "instant": false,
          "legendFormat": "Rousing Earth, {{quantile}}",
          "range": true,
          "refId": "A"
        },
        {
          "datasource": {
            "type": "prometheus",
            "uid": "I50WY3hVz"
          },
          "editorMode": "code",
          "exemplar": false,
          "expr": "auction_price_gold{name=\"Awakened Earth\", quantile=\"$percentile\"}",
          "format": "time_series",
          "hide": false,
          "instant": false,
          "legendFormat": "Awakened Earth, {{quantile}}",
          "range": true,
          "refId": "B"
        }
      ],
      "title": "Earth Essence",
      "type": "timeseries"
    },
    {
      "datasource": {
        "type": "prometheus",
        "uid": "I50WY3hVz"
      },
      "description": "",
      "fieldConfig": {
        "defaults": {
          "color": {
            "mode": "palette-classic"
          },
          "custom": {
            "axisLabel": "",
            "axisPlacement": "auto",
            "barAlignment": 0,
            "drawStyle": "line",
            "fillOpacity": 0,
            "gradientMode": "none",
            "hideFrom": {
              "legend": false,
              "tooltip": false,
              "viz": false
            },
            "lineInterpolation": "linear",
            "lineWidth": 1,
            "pointSize": 5,
            "scaleDistribution": {
              "type": "linear"
            },
            "showPoints": "auto",
            "spanNulls": false,
            "stacking": {
              "group": "A",
              "mode": "none"
            },
            "thresholdsStyle": {
              "mode": "off"
            }
          },
          "mappings": [],
          "thresholds": {
            "mode": "absolute",
            "steps": [
              {
                "color": "green",
                "value": null
              },
              {
                "color": "red",
                "value": 80
              }
            ]
          }
        },
        "overrides": []
      },
      "gridPos": {
        "h": 8,
        "w": 4,
        "x": 4,
        "y": 36
      },
      "id": 12,
      "options": {
        "legend": {
          "calcs": [],
          "displayMode": "list",
          "placement": "bottom"
        },
        "tooltip": {
          "mode": "single",
          "sort": "none"
        }
      },
      "targets": [
        {
          "datasource": {
            "type": "prometheus",
            "uid": "I50WY3hVz"
          },
          "editorMode": "code",
          "exemplar": false,
          "expr": "auction_price_gold{name=\"Rousing Ire\", quantile=\"$percentile\"}",
          "format": "time_series",
          "hide": false,
          "instant": false,
          "legendFormat": "Rousing Ire, {{quantile}}",
          "range": true,
          "refId": "A"
        },
        {
          "datasource": {
            "type": "prometheus",
            "uid": "I50WY3hVz"
          },
          "editorMode": "code",
          "exemplar": false,
          "expr": "auction_price_gold{name=\"Awakened Ire\", quantile=\"$percentile\"}",
          "format": "time_series",
          "hide": false,
          "instant": false,
          "legendFormat": "Awakened Ire, {{quantile}}",
          "range": true,
          "refId": "B"
        }
      ],
      "title": "Ire Essence",
      "type": "timeseries"
    },
    {
      "datasource": {
        "type": "prometheus",
        "uid": "I50WY3hVz"
      },
      "description": "",
      "fieldConfig": {
        "defaults": {
          "color": {
            "mode": "palette-classic"
          },
          "custom": {
            "axisLabel": "",
            "axisPlacement": "auto",
            "barAlignment": 0,
            "drawStyle": "line",
            "fillOpacity": 0,
            "gradientMode": "none",
            "hideFrom": {
              "legend": false,
              "tooltip": false,
              "viz": false
            },
            "lineInterpolation": "linear",
            "lineWidth": 1,
            "pointSize": 5,
            "scaleDistribution": {
              "type": "linear"
            },
            "showPoints": "auto",
            "spanNulls": false,
            "stacking": {
              "group": "A",
              "mode": "none"
            },
            "thresholdsStyle": {
              "mode": "off"
            }
          },
          "mappings": [],
          "thresholds": {
            "mode": "absolute",
            "steps": [
              {
                "color": "green",
                "value": null
              },
              {
                "color": "red",
                "value": 80
              }
            ]
          }
        },
        "overrides": []
      },
      "gridPos": {
        "h": 8,
        "w": 4,
        "x": 8,
        "y": 36
      },
      "id": 15,
      "options": {
        "legend": {
          "calcs": [],
          "displayMode": "list",
          "placement": "bottom"
        },
        "tooltip": {
          "mode": "single",
          "sort": "none"
        }
      },
      "targets": [
        {
          "datasource": {
            "type": "prometheus",
            "uid": "I50WY3hVz"
          },
          "editorMode": "code",
          "exemplar": false,
          "expr": "auction_price_gold{name=\"Rousing Order\", quantile=\"$percentile\"}",
          "format": "time_series",
          "hide": false,
          "instant": false,
          "legendFormat": "Rousing Order, {{quantile}}",
          "range": true,
          "refId": "A"
        },
        {
          "datasource": {
            "type": "prometheus",
            "uid": "I50WY3hVz"
          },
          "editorMode": "code",
          "exemplar": false,
          "expr": "auction_price_gold{name=\"Awakened Order\", quantile=\"$percentile\"}",
          "format": "time_series",
          "hide": false,
          "instant": false,
          "legendFormat": "Awakened Order, {{quantile}}",
          "range": true,
          "refId": "B"
        }
      ],
      "title": "Order Essence",
      "type": "timeseries"
    },
    {
      "datasource": {
        "type": "prometheus",
        "uid": "I50WY3hVz"
      },
      "description": "",
      "fieldConfig": {
        "defaults": {
          "color": {
            "mode": "palette-classic"
          },
          "custom": {
            "axisLabel": "",
            "axisPlacement": "auto",
            "barAlignment": 0,
            "drawStyle": "line",
            "fillOpacity": 0,
            "gradientMode": "none",
            "hideFrom": {
              "legend": false,
              "tooltip": false,
              "viz": false
            },
            "lineInterpolation": "linear",
            "lineWidth": 1,
            "pointSize": 5,
            "scaleDistribution": {
              "type": "linear"
            },
            "showPoints": "auto",
            "spanNulls": false,
            "stacking": {
              "group": "A",
              "mode": "none"
            },
            "thresholdsStyle": {
              "mode": "off"
            }
          },
          "mappings": [],
          "thresholds": {
            "mode": "absolute",
            "steps": [
              {
                "color": "green",
                "value": null
              },
              {
                "color": "red",
                "value": 80
              }
            ]
          }
        },
        "overrides": []
      },
      "gridPos": {
        "h": 8,
        "w": 4,
        "x": 12,
        "y": 36
      },
      "id": 16,
      "options": {
        "legend": {
          "calcs": [],
          "displayMode": "list",
          "placement": "bottom"
        },
        "tooltip": {
          "mode": "single",
          "sort": "none"
        }
      },
      "targets": [
        {
          "datasource": {
            "type": "prometheus",
            "uid": "I50WY3hVz"
          },
          "editorMode": "code",
          "exemplar": false,
          "expr": "auction_price_gold{name=\"Rousing Decay\", quantile=\"$percentile\"}",
          "format": "time_series",
          "hide": false,
          "instant": false,
          "legendFormat": "Rousing Decay, {{quantile}}",
          "range": true,
          "refId": "A"
        },
        {
          "datasource": {
            "type": "prometheus",
            "uid": "I50WY3hVz"
          },
          "editorMode": "code",
          "exemplar": false,
          "expr": "auction_price_gold{name=\"Awakened Decay\", quantile=\"$percentile\"}",
          "format": "time_series",
          "hide": false,
          "instant": false,
          "legendFormat": "Awakened Decay, {{quantile}}",
          "range": true,
          "refId": "B"
        }
      ],
      "title": "Decay Essence",
      "type": "timeseries"
    },
    {
      "datasource": {
        "type": "prometheus",
        "uid": "I50WY3hVz"
      },
      "description": "",
      "fieldConfig": {
        "defaults": {
          "color": {
            "mode": "palette-classic"
          },
          "custom": {
            "axisLabel": "",
            "axisPlacement": "auto",
            "barAlignment": 0,
            "drawStyle": "line",
            "fillOpacity": 0,
            "gradientMode": "none",
            "hideFrom": {
              "legend": false,
              "tooltip": false,
              "viz": false
            },
            "lineInterpolation": "linear",
            "lineWidth": 1,
            "pointSize": 5,
            "scaleDistribution": {
              "type": "linear"
            },
            "showPoints": "auto",
            "spanNulls": false,
            "stacking": {
              "group": "A",
              "mode": "none"
            },
            "thresholdsStyle": {
              "mode": "off"
            }
          },
          "mappings": [],
          "thresholds": {
            "mode": "absolute",
            "steps": [
              {
                "color": "green",
                "value": null
              },
              {
                "color": "red",
                "value": 80
              }
            ]
          }
        },
        "overrides": []
      },
      "gridPos": {
        "h": 8,
        "w": 4,
        "x": 16,
        "y": 36
      },
      "id": 19,
      "options": {
        "legend": {
          "calcs": [],
          "displayMode": "list",
          "placement": "bottom"
        },
        "tooltip": {
          "mode": "single",
          "sort": "none"
        }
      },
      "targets": [
        {
          "datasource": {
            "type": "prometheus",
            "uid": "I50WY3hVz"
          },
          "editorMode": "code",
          "exemplar": false,
          "expr": "auction_price_gold{name=\"Rousing Frost\", quantile=\"$percentile\"}",
          "format": "time_series",
          "hide": false,
          "instant": false,
          "legendFormat": "Rousing Frost, {{quantile}}",
          "range": true,
          "refId": "A"
        },
        {
          "datasource": {
            "type": "prometheus",
            "uid": "I50WY3hVz"
          },
          "editorMode": "code",
          "exemplar": false,
          "expr": "auction_price_gold{name=\"Awakened Frost\", quantile=\"$percentile\"}",
          "format": "time_series",
          "hide": false,
          "instant": false,
          "legendFormat": "Awakened Frost, {{quantile}}",
          "range": true,
          "refId": "B"
        }
      ],
      "title": "Frost Essence",
      "type": "timeseries"
    },
    {
      "datasource": {
        "type": "prometheus",
        "uid": "I50WY3hVz"
      },
      "description": "",
      "fieldConfig": {
        "defaults": {
          "color": {
            "mode": "palette-classic"
          },
          "custom": {
            "axisLabel": "",
            "axisPlacement": "auto",
            "barAlignment": 0,
            "drawStyle": "line",
            "fillOpacity": 0,
            "gradientMode": "none",
            "hideFrom": {
              "legend": false,
              "tooltip": false,
              "viz": false
            },
            "lineInterpolation": "linear",
            "lineWidth": 1,
            "pointSize": 5,
            "scaleDistribution": {
              "type": "linear"
            },
            "showPoints": "auto",
            "spanNulls": false,
            "stacking": {
              "group": "A",
              "mode": "none"
            },
            "thresholdsStyle": {
              "mode": "off"
            }
          },
          "mappings": [],
          "thresholds": {
            "mode": "absolute",
            "steps": [
              {
                "color": "green",
                "value": null
              },
              {
                "color": "red",
                "value": 80
              }
            ]
          }
        },
        "overrides": []
      },
      "gridPos": {
        "h": 8,
        "w": 4,
        "x": 20,
        "y": 36
      },
      "id": 20,
      "options": {
        "legend": {
          "calcs": [],
          "displayMode": "list",
          "placement": "bottom"
        },
        "tooltip": {
          "mode": "single",
          "sort": "none"
        }
      },
      "targets": [
        {
          "datasource": {
            "type": "prometheus",
            "uid": "I50WY3hVz"
          },
          "editorMode": "code",
          "exemplar": false,
          "expr": "auction_price_gold{name=\"Rousing Fire\", quantile=\"$percentile\"}",
          "format": "time_series",
          "hide": false,
          "instant": false,
          "legendFormat": "Rousing Fire, {{quantile}}",
          "range": true,
          "refId": "A"
        },
        {
          "datasource": {
            "type": "prometheus",
            "uid": "I50WY3hVz"
          },
          "editorMode": "code",
          "exemplar": false,
          "expr": "auction_price_gold{name=\"Awakened Fire\", quantile=\"$percentile\"}",
          "format": "time_series",
          "hide": false,
          "instant": false,
          "legendFormat": "Awakened Fire, {{quantile}}",
          "range": true,
          "refId": "B"
        }
      ],
      "title": "Fire Essence",
      "type": "timeseries"
    }
  ],
  "refresh": false,
  "schemaVersion": 36,
  "style": "dark",
  "tags": [],
  "templating": {
    "list": [
      {
        "current": {
          "selected": true,
          "text": "0.95",
          "value": "0.95"
        },
        "hide": 0,
        "includeAll": false,
        "label": "Percentile",
        "multi": false,
        "name": "percentile",
        "options": [
          {
            "selected": false,
            "text": "0.5",
            "value": "0.5"
          },
          {
            "selected": false,
            "text": "0.75",
            "value": "0.75"
          },
          {
            "selected": false,
            "text": "0.9",
            "value": "0.9"
          },
          {
            "selected": true,
            "text": "0.95",
            "value": "0.95"
          },
          {
            "selected": false,
            "text": "0.99",
            "value": "0.99"
          },
          {
            "selected": false,
            "text": "0.999",
            "value": "0.999"
          },
          {
            "selected": false,
            "text": "1",
            "value": "1"
          }
        ],
        "query": "0.5, 0.75, 0.9, 0.95, 0.99, 0.999, 1",
        "queryValue": "",
        "skipUrlSync": false,
        "type": "custom"
      }
    ]
  },
  "time": {
    "from": "now-6h",
    "to": "now"
  },
  "timepicker": {},
  "timezone": "",
  "title": "Auctions",
  "uid": "HAXFY3hVz",
  "version": 7,
  "weekStart": ""
}